Metadata-Version: 1.0
Name: flv2img0.0.3
Version: 0.0.3
Summary: just a simple test of vipkid
Home-page: UNKNOWN
Author: yin
Author-email: yinmengmeng@vipkid.com.cn
License: MIT
Keywords: simple,test
Platform: any
